mediathequeroubaix/__init__.py
mediathequeroubaix/__main__.py
mediathequeroubaix/config.py
mediathequeroubaix/loans.py
mediathequeroubaix/main.py
mediathequeroubaix/py.typed
mediathequeroubaix/auth/__init__.py
mediathequeroubaix/auth/authenticate.py
mediathequeroubaix/auth/authenticate_test.py
mediathequeroubaix/auth/authenticated_session.py
mediathequeroubaix/auth/get_user.py
mediathequeroubaix/auth/get_user_test.py
mediathequeroubaix/get_loans/__init__.py
mediathequeroubaix/get_loans/base64decode.py
mediathequeroubaix/get_loans/base64decode_test.py
mediathequeroubaix/get_loans/extract_token.py
mediathequeroubaix/get_loans/extract_token_test.py
mediathequeroubaix/get_loans/get_loans.py
mediathequeroubaix/get_loans/get_loans_test.py
mediathequeroubaix/get_loans/loan.py
mediathequeroubaix/get_loans/loan_test.py
mediathequeroubaix/get_loans/parse_loans.py
mediathequeroubaix/get_loans/parse_loans_test.py
mediathequeroubaix/renew/__init__.py
mediathequeroubaix/renew/renew.py
mediathequeroubaix/renew/renew_test.py
mediathequeroubaix-1.5.0.dist-info/METADATA
mediathequeroubaix-1.5.0.dist-info/WHEEL
mediathequeroubaix-1.5.0.dist-info/entry_points.txt
mediathequeroubaix-1.5.0.dist-info/licenses/LICENSE.txt
mediathequeroubaix-1.5.0.dist-info/RECORD
