Metadata-Version: 2.3
Name: mediathequeroubaix
Version: 1.5.0
Summary: Client for the library of Roubaix (Médiathèque Roubaix)
Project-URL: Changelog, https://github.com/tomsquest/mediathequeroubaix.py/blob/master/CHANGELOG.md
Project-URL: Releases, https://github.com/tomsquest/mediathequeroubaix.py/releases
Project-URL: Repository, https://github.com/tomsquest/mediathequeroubaix.py
Author-email: Thomas Queste <tom@tomsquest.com>
License: The MIT License (MIT)
License-File: LICENSE.txt
Classifier: Development Status :: 5 - Production/Stable
Classifier: Environment :: Console
Classifier: Intended Audience :: End Users/Desktop
Classifier: Programming Language :: Python :: 3.12
Classifier: Typing :: Typed
Requires-Python: >=3.12
Requires-Dist: pydantic-settings>=2.6.1
Requires-Dist: pydantic>=1.10.2
Requires-Dist: requests>=2.28.1
Requires-Dist: returns>=0.23.0
Requires-Dist: rich>=12.6.0
Requires-Dist: typer>=0.7.0
